[
  {"id": "A5020744800", "name": "Peter W. Shor"},
  {"id": "A5061874000", "name": "John Preskill"},
  {"id": "A5020769134", "name": "Scott Aaronson"},
  {"id": "A5053166798", "name": "Charles H. Bennett"},
  {"id": "A5050850280", "name": "David Deutsch"},
  {"id": "A5037710835", "name": "Richard P. Feynman"},
  {"id": "A5038060570", "name": "Seth Lloyd"},
  {"id": "A5031023857", "name": "Lov K. Grover"},
  {"id": "A5083228566", "name": "J. Ignacio Cirac"},
  {"id": "A5016282235", "name": "Peter Zoller"},
  {"id": "A5040977712", "name": "Rainer Blatt"},
  {"id": "A5005759724", "name": "Christopher Monroe"},
  {"id": "A5066245772", "name": "Mikhail D. Lukin"},
  {"id": "A5042449260", "name": "Jian-Wei Pan"},
  {"id": "A5059030616", "name": "Artur Ekert"},
  {"id": "A5001105113", "name": "Anton Zeilinger"},
  {"id": "A5046427077", "name": "Alain Aspect"},
  {"id": "A5001536933", "name": "David J. Wineland"},
  {"id": "A5108398851", "name": "Serge Haroche"},
  {"id": "A5078255491", "name": "Raymond Laflamme"},
  {"id": "A5006327208", "name": "Daniel Gottesman"},
  {"id": "A5027759442", "name": "Alexei Kitaev"},
  {"id": "A5068097121", "name": "Michael A. Nielsen"},
  {"id": "A5103046966", "name": "Isaac L. Chuang"},
  {"id": "A5036253306", "name": "Edward Farhi"},
  {"id": "A5018837979", "name": "Andrew M. Childs"},
  {"id": "A5058819109", "name": "Barbara M. Terhal"},
  {"id": "A5001154267", "name": "Frank Verstraete"},
  {"id": "A5111058882", "name": "Guifre Vidal"},
  {"id": "A5043106778", "name": "John M. Martinis"},
  {"id": "A5012231169", "name": "Hartmut Neven"},
  {"id": "A5084929692", "name": "Robert Schoelkopf"},
  {"id": "A5089631322", "name": "Michel Devoret"},
  {"id": "A5016075205", "name": "Andreas Wallraff"},
  {"id": "A5064155719", "name": "Michael Freedman"},
  {"id": "A5060980314", "name": "Sankar Das Sarma"},
  {"id": "A5006639172", "name": "Charles M. Marcus"},
  {"id": "A5103068314", "name": "Leo P. Kouwenhoven"},
  {"id": "A5030701195", "name": "Jay Gambetta"},
  {"id": "A5064909614", "name": "Andrew W. Cross"},
  {"id": "A5071105459", "name": "Patrick Hayden"},
  {"id": "A5005794608", "name": "Dorit Aharonov"},
  {"id": "A5071039750", "name": "Umesh Vazirani"},
  {"id": "A5066563480", "name": "Ronald de Wolf"},
  {"id": "A5023685398", "name": "Ashley Montanaro"},
  {"id": "A5028440699", "name": "Matthias Troyer"},
  {"id": "A5019716296", "name": "Krysta M. Svore"},
  {"id": "A5032976159", "name": "Robin Blume-Kohout"},
  {"id": "A5046083937", "name": "Steven M. Girvin"},
  {"id": "A5068826612", "name": "Liang Jiang"},
  {"id": "A5004169905", "name": "Maissam Barkeshli"},
  {"id": "A5008766821", "name": "Aram W. Harrow"},
  {"id": "A5078065002", "name": "William K. Wootters"},
  {"id": "A5110284072", "name": "Gilles Brassard"},
  {"id": "A5056095913", "name": "David P. DiVincenzo"},
  {"id": "A5010879789", "name": "Daniel Loss"},
  {"id": "A5012503150", "name": "Lieven M. K. Vandersypen"},
  {"id": "A5049405877", "name": "Michelle Simmons"},
  {"id": "A5047414815", "name": "Andrea Morello"},
  {"id": "A5027716155", "name": "Winfried Hensinger"},
  {"id": "A5082160956", "name": "Tracy E. Northup"},
  {"id": "A5065994445", "name": "Ben W. Reichardt"},
  {"id": "A5066295139", "name": "Thomas Monz"},
  {"id": "A5052107957", "name": "Elham Kashefi"},
  {"id": "A5034032202", "name": "Anne Broadbent"},
  {"id": "A5039127008", "name": "Naomi Nickerson"},
  {"id": "A5018132307", "name": "Earl T. Campbell"},
  {"id": "A5012132706", "name": "Simon C. Benjamin"},
  {"id": "A5090412627", "name": "Xiao Yuan"},
  {"id": "A5073521804", "name": "Pedram Roushan"},
  {"id": "A5065681671", "name": "Sergio Boixo"},
  {"id": "A5030940558", "name": "Fernando G. S. L. Brandão"},
  {"id": "A5019616211", "name": "Thomas Vidick"},
  {"id": "A5023852532", "name": "Zvika Brakerski"},
  {"id": "A5011207998", "name": "Urmila Mahadev"},
  {"id": "A5020583189", "name": "Ewin Tang"},
  {"id": "A5024414185", "name": "Shruti Puri"},
  {"id": "A5007129549", "name": "Steven T. Flammia"},
  {"id": "A5009791247", "name": "Dolev Bluvstein"},
  {"id": "A5003369827", "name": "Harry Levine"},
  {"id": "A5110481134", "name": "Vladan Vuletić"}
]
